archive_unused_files.py
archive_unused_images.py
check_published_links.py
check_scannability.py
check_source_directives.py
convert_callouts_interactive.py
convert_callouts_to_deflist.py
convert_freemarker_to_asciidoc.py
convert_tables_to_deflists.py
doc_utils_cli.py
extract_link_attributes.py
find_duplicate_content.py
find_duplicate_includes.py
find_unused_attributes.py
format_asciidoc_spacing.py
insert_abstract_role.py
inventory_conditionals.py
replace_link_attributes.py
validate_links.py
callout_lib/__init__.py
callout_lib/converter_bullets.py
callout_lib/converter_comments.py
callout_lib/converter_deflist.py
callout_lib/detector.py
callout_lib/table_parser.py
doc_utils/__init__.py
doc_utils/convert_freemarker_to_asciidoc.py
doc_utils/duplicate_content.py
doc_utils/duplicate_includes.py
doc_utils/extract_link_attributes.py
doc_utils/file_utils.py
doc_utils/format_asciidoc_spacing.py
doc_utils/insert_abstract_role.py
doc_utils/inventory_conditionals.py
doc_utils/missing_source_directive.py
doc_utils/replace_link_attributes.py
doc_utils/scannability.py
doc_utils/spinner.py
doc_utils/topic_map_parser.py
doc_utils/unused_adoc.py
doc_utils/unused_attributes.py
doc_utils/unused_images.py
doc_utils/validate_links.py
doc_utils/version.py
doc_utils/version_check.py
doc_utils/warnings_report.py
rolfedh_doc_utils-0.1.41.dist-info/licenses/LICENSE
rolfedh_doc_utils-0.1.41.dist-info/METADATA
rolfedh_doc_utils-0.1.41.dist-info/WHEEL
rolfedh_doc_utils-0.1.41.dist-info/entry_points.txt
rolfedh_doc_utils-0.1.41.dist-info/top_level.txt
rolfedh_doc_utils-0.1.41.dist-info/RECORD
