Metadata-Version: 2.4
Name: rolfedh-doc-utils
Version: 0.1.41
Summary: CLI tools for AsciiDoc documentation projects
Author: Rolfe Dlugy-Hegwer
License: MIT License
Requires-Python: >=3.8
License-File: LICENSE
Requires-Dist: PyYAML>=6.0
Dynamic: license-file
